README.md
setup.py
zscaler_pulumi_zia/__init__.py
zscaler_pulumi_zia/_inputs.py
zscaler_pulumi_zia/_utilities.py
zscaler_pulumi_zia/activation_status.py
zscaler_pulumi_zia/admin_roles.py
zscaler_pulumi_zia/admin_users.py
zscaler_pulumi_zia/advanced_settings.py
zscaler_pulumi_zia/advanced_threat_settings.py
zscaler_pulumi_zia/atp_malicious_urls.py
zscaler_pulumi_zia/atp_malware_inspection.py
zscaler_pulumi_zia/atp_malware_policy.py
zscaler_pulumi_zia/atp_malware_protocols.py
zscaler_pulumi_zia/atp_malware_settings.py
zscaler_pulumi_zia/atp_security_exceptions.py
zscaler_pulumi_zia/auth_settings_urls.py
zscaler_pulumi_zia/browser_control_policy.py
zscaler_pulumi_zia/browser_control_settings.py
zscaler_pulumi_zia/casb_dlp_rule.py
zscaler_pulumi_zia/casb_dlp_rules.py
zscaler_pulumi_zia/casb_malware_rule.py
zscaler_pulumi_zia/casb_malware_rules.py
zscaler_pulumi_zia/cloud_app_control_rule.py
zscaler_pulumi_zia/cloud_application_instance.py
zscaler_pulumi_zia/dlp_dictionaries.py
zscaler_pulumi_zia/dlp_engines.py
zscaler_pulumi_zia/dlp_notification_templates.py
zscaler_pulumi_zia/dlp_web_rules.py
zscaler_pulumi_zia/end_user_notification.py
zscaler_pulumi_zia/file_type_control_rules.py
zscaler_pulumi_zia/firewall_dns_rule.py
zscaler_pulumi_zia/firewall_filtering_application_groups.py
zscaler_pulumi_zia/firewall_filtering_destination_groups.py
zscaler_pulumi_zia/firewall_filtering_network_services.py
zscaler_pulumi_zia/firewall_filtering_rule.py
zscaler_pulumi_zia/firewall_filtering_service_groups.py
zscaler_pulumi_zia/firewall_filtering_source_groups.py
zscaler_pulumi_zia/firewall_ips_rule.py
zscaler_pulumi_zia/forwarding_control_proxies.py
zscaler_pulumi_zia/forwarding_control_rule.py
zscaler_pulumi_zia/forwarding_control_zpa_gateway.py
zscaler_pulumi_zia/ftp_control_policy.py
zscaler_pulumi_zia/get_activation_status.py
zscaler_pulumi_zia/get_admin_roles.py
zscaler_pulumi_zia/get_admin_users.py
zscaler_pulumi_zia/get_advanced_settings.py
zscaler_pulumi_zia.egg-info/PKG-INFO
zscaler_pulumi_zia.egg-info/SOURCES.txt
zscaler_pulumi_zia.egg-info/dependency_links.txt
zscaler_pulumi_zia.egg-info/not-zip-safe
zscaler_pulumi_zia.egg-info/requires.txt
zscaler_pulumi_zia.egg-info/top_level.txt
