Metadata-Version: 2.1
Name: zscaler-pulumi-zia
Version: 1.1.1
Summary: A Pulumi package for creating and managing zia cloud resources.
Home-page: https://www.zscaler.com
License: MIT
Project-URL: Repository, https://github.com/zscaler/pulumi-zia
Keywords: pulumi zia zscaler category/cloud
Platform: UNKNOWN
Requires-Python: >=3.9
